{
  "status": 1,
  "message": "Data set is ready.",
  "data": [
    {
      "time": "2025-09-15T15:24:35.671862148Z",
      "address": "sbi.com.in",
      "avg_rtt": null,
      "destination": "sbi.com.in",
      "id": "b7ee6c91-e6e5-405c-8331-300534282d3f",
      "is_alive": true,
      "jitter": 0.095,
      "max_rtt": null,
      "min_rtt": null,
      "packet_duplicate_count": null,
      "packet_duplicate_rate": null,
      "packet_loss": 0,
      "packet_loss_count": null,
      "packet_loss_rate": null,
      "packet_receive": null,
      "packet_transmit": null,
      "packets_received": 3,
      "packets_sent": 3,
      "port": null,
      "protocol": "ICMP",
      "protocol_1": "ICMP",
      "rd3": "9d899cb874c51f77befdfaa0fd055e41",
      "rtt_avg": 2.21,
      "rtt_max": 2.273,
      "rtt_mdev": null,
      "rtt_min": 2.15,
      "anchor_name": "IN-V2-168"
    },
    {
      "time": "2025-09-15T15:24:35.672961051Z",
      "address": "sbi.com.in",
      "avg_rtt": null,
      "destination": "sbi.com.in",
      "id": "b7ee6c91-e6e5-405c-8331-300534282d3f",
      "is_alive": true,
      "jitter": 0.095,
      "max_rtt": null,
      "min_rtt": null,
      "packet_duplicate_count": null,
      "packet_duplicate_rate": null,
      "packet_loss": 0,
      "packet_loss_count": null,
      "packet_loss_rate": null,
      "packet_receive": null,
      "packet_transmit": null,
      "packets_received": 3,
      "packets_sent": 3,
      "port": null,
      "protocol": "ICMP",
      "protocol_1": "ICMP",
      "rd3": "9d899cb874c51f77befdfaa0fd055e41",
      "rtt_avg": 2.21,
      "rtt_max": 2.273,
      "rtt_mdev": null,
      "rtt_min": 2.15,
      "anchor_name": "IN-V2-168"
    },
    {
      "time": "2025-09-15T15:24:35.673600474Z",
      "address": "sbi.com.in",
      "avg_rtt": null,
      "destination": "sbi.com.in",
      "id": "b7ee6c91-e6e5-405c-8331-300534282d3f",
      "is_alive": true,
      "jitter": 0.095,
      "max_rtt": null,
      "min_rtt": null,
      "packet_duplicate_count": null,
      "packet_duplicate_rate": null,
      "packet_loss": 0,
      "packet_loss_count": null,
      "packet_loss_rate": null,
      "packet_receive": null,
      "packet_transmit": null,
      "packets_received": 3,
      "packets_sent": 3,
      "port": null,
      "protocol": "ICMP",
      "protocol_1": "ICMP",
      "rd3": "9d899cb874c51f77befdfaa0fd055e41",
      "rtt_avg": 2.21,
      "rtt_max": 2.273,
      "rtt_mdev": null,
      "rtt_min": 2.15,
      "anchor_name": "IN-V2-168"
    },
    {
      "time": "2025-09-15T15:24:35.679713917Z",
      "address": "sbi.com.in",
      "avg_rtt": null,
      "destination": "sbi.com.in",
      "id": "b7ee6c91-e6e5-405c-8331-300534282d3f",
      "is_alive": true,
      "jitter": 0.095,
      "max_rtt": null,
      "min_rtt": null,
      "packet_duplicate_count": null,
      "packet_duplicate_rate": null,
      "packet_loss": 0,
      "packet_loss_count": null,
      "packet_loss_rate": null,
      "packet_receive": null,
      "packet_transmit": null,
      "packets_received": 3,
      "packets_sent": 3,
      "port": null,
      "protocol": "ICMP",
      "protocol_1": "ICMP",
      "rd3": "9d899cb874c51f77befdfaa0fd055e41",
      "rtt_avg": 2.21,
      "rtt_max": 2.273,
      "rtt_mdev": null,
      "rtt_min": 2.15,
      "anchor_name": "IN-V2-168"
    },
    {
      "time": "2025-09-15T15:24:35.842717657Z",
      "address": "sbi.com.in",
      "avg_rtt": null,
      "destination": "sbi.com.in",
      "id": "b7ee6c91-e6e5-405c-8331-300534282d3f",
      "is_alive": true,
      "jitter": 0.095,
      "max_rtt": null,
      "min_rtt": null,
      "packet_duplicate_count": null,
      "packet_duplicate_rate": null,
      "packet_loss": 0,
      "packet_loss_count": null,
      "packet_loss_rate": null,
      "packet_receive": null,
      "packet_transmit": null,
      "packets_received": 3,
      "packets_sent": 3,
      "port": null,
      "protocol": "ICMP",
      "protocol_1": "ICMP",
      "rd3": "9d899cb874c51f77befdfaa0fd055e41",
      "rtt_avg": 2.21,
      "rtt_max": 2.273,
      "rtt_mdev": null,
      "rtt_min": 2.15,
      "anchor_name": "IN-V2-168"
    },
    {
      "time": "2025-09-15T15:24:35.842739252Z",
      "address": "sbi.com.in",
      "avg_rtt": null,
      "destination": "sbi.com.in",
      "id": "b7ee6c91-e6e5-405c-8331-300534282d3f",
      "is_alive": true,
      "jitter": 0.095,
      "max_rtt": null,
      "min_rtt": null,
      "packet_duplicate_count": null,
      "packet_duplicate_rate": null,
      "packet_loss": 0,
      "packet_loss_count": null,
      "packet_loss_rate": null,
      "packet_receive": null,
      "packet_transmit": null,
      "packets_received": 3,
      "packets_sent": 3,
      "port": null,
      "protocol": "ICMP",
      "protocol_1": "ICMP",
      "rd3": "9d899cb874c51f77befdfaa0fd055e41",
      "rtt_avg": 2.21,
      "rtt_max": 2.273,
      "rtt_mdev": null,
      "rtt_min": 2.15,
      "anchor_name": "IN-V2-168"
    }
  ]
}